pixelhosting/__init__.py
pixelhosting/pixelhosting.py
pixelhosting-0.1.1.dist-info/METADATA
pixelhosting-0.1.1.dist-info/RECORD
pixelhosting-0.1.1.dist-info/WHEEL
pixelhosting-0.1.1.dist-info/top_level.txt
